djangocms_moderation/__init__.py
djangocms_moderation/admin.py
djangocms_moderation/admin_actions.py
djangocms_moderation/apps.py
djangocms_moderation/backends.py
djangocms_moderation/cms_config.py
djangocms_moderation/cms_toolbars.py
djangocms_moderation/compact.py
djangocms_moderation/conf.py
djangocms_moderation/constants.py
djangocms_moderation/emails.py
djangocms_moderation/exceptions.py
djangocms_moderation/filters.py
djangocms_moderation/forms.py
djangocms_moderation/handlers.py
djangocms_moderation/helpers.py
djangocms_moderation/managers.py
djangocms_moderation/models.py
djangocms_moderation/monkeypatch.py
djangocms_moderation/signals.py
djangocms_moderation/utils.py
djangocms_moderation/views.py
djangocms_moderation/locale/en/LC_MESSAGES/django.po
djangocms_moderation/management/__init__.py
djangocms_moderation/management/commands/__init__.py
djangocms_moderation/management/commands/moderation_fix_states.py
djangocms_moderation/migrations/0001_initial.py
djangocms_moderation/migrations/0001_squashed_0017_auto_20220831_0727.py
djangocms_moderation/migrations/0002_auto_20180905_1152.py
djangocms_moderation/migrations/0003_auto_20180903_1206.py
djangocms_moderation/migrations/0004_auto_20180907_1206.py
djangocms_moderation/migrations/0005_auto_20180919_1348.py
djangocms_moderation/migrations/0006_auto_20181001_1840.py
djangocms_moderation/migrations/0007_auto_20181002_1725.py
djangocms_moderation/migrations/0008_auto_20181002_1833.py
djangocms_moderation/migrations/0009_auto_20181005_1534.py
djangocms_moderation/migrations/0010_auto_20181008_1317.py
djangocms_moderation/migrations/0011_auto_20181008_1328.py
djangocms_moderation/migrations/0012_auto_20181016_1319.py
djangocms_moderation/migrations/0013_auto_20181122_1110.py
djangocms_moderation/migrations/0014_auto_20190313_1638.py
djangocms_moderation/migrations/0014_auto_20190315_1723.py
djangocms_moderation/migrations/0016_moderationrequesttreenode.py
djangocms_moderation-2.2.3.dist-info/licenses/LICENSE.txt
djangocms_moderation-2.2.3.dist-info/METADATA
djangocms_moderation-2.2.3.dist-info/WHEEL
djangocms_moderation-2.2.3.dist-info/top_level.txt
djangocms_moderation-2.2.3.dist-info/RECORD
