Metadata-Version: 2.4
Name: djangocms-moderation
Version: 2.2.3
Summary: Provide moderation workflows for content in Django CMS
Author-email: Divio AG <info@divio.ch>
Maintainer-email: Django CMS Association and contributors <info@django-cms.org>
License: BSD
Project-URL: Homepage, https://github.com/django-cms/djangocms-moderation
Project-URL: Repository, https://github.com/django-cms/djangocms-moderation
Project-URL: Documentation, https://github.com/django-cms/djangocms-moderation
Project-URL: Bug Tracker, https://github.com/django-cms/djangocms-moderation/issues
Classifier: Development Status :: 5 - Production/Stable
Classifier: Programming Language :: Python
Classifier: Programming Language :: Python :: 3.10
Classifier: Programming Language :: Python :: 3.11
Classifier: Programming Language :: Python :: 3.12
Classifier: Framework :: Django
Classifier: Framework :: Django :: 3.2
Classifier: Framework :: Django :: 4.2
Classifier: Framework :: Django :: 5.0
Classifier: Framework :: Django CMS
Classifier: Framework :: Django CMS :: 4.0
Classifier: Framework :: Django CMS :: 4.1
Classifier: Intended Audience :: Developers
Classifier: License :: OSI Approved :: BSD License
Classifier: Operating System :: OS Independent
Classifier: Topic :: Software Development
Requires-Python: >=3.10
License-File: LICENSE.txt
Requires-Dist: Django>=3.2
Requires-Dist: django-cms
Requires-Dist: django-sekizai>=0.7
Requires-Dist: django-admin-sortable2>=0.6.4
Dynamic: license-file
